bdating_common/__init__.py
bdating_common/api_common.py
bdating_common/auth0_management_helper.py
bdating_common/auth0_token_helper.py
bdating_common/aws_secrets_helper.py
bdating_common/collect_default.py
bdating_common/crypto_helper.py
bdating_common/enum_translation.yml
bdating_common/errors.py
bdating_common/es_helper.py
bdating_common/event_helper.py
bdating_common/in_app_notif_helper.py
bdating_common/json_logger.py
bdating_common/model.py
bdating_common/multi_threading.py
bdating_common/notify_helper.py
bdating_common/report_metrics.py
bdating_common/schedule_helper.py
bdating_common/time_helper.py
bdating_common/utils.py
bdating_common/wallet_helper.py
bdating_common-0.9.18.dist-info/METADATA
bdating_common-0.9.18.dist-info/WHEEL
bdating_common-0.9.18.dist-info/entry_points.txt
bdating_common-0.9.18.dist-info/top_level.txt
bdating_common-0.9.18.dist-info/RECORD
