Metadata-Version: 2.1
Name: bdating-common
Version: 0.9.18
Summary: Bdating common libraries standard library
Home-page: https://github.com/bdating-io/bdating-python-common
Author: Zac
Author-email: zac@bdating.io
License: UNKNOWN
Platform: UNKNOWN
Classifier: Intended Audience :: Developers
Classifier: Programming Language :: Python :: 3 :: Only
Classifier: Topic :: Utilities
Classifier: Typing :: Typed
Requires-Python: >=3.6
Requires-Dist: PyJWT (==2.1.0)
Requires-Dist: PyMySQL
Requires-Dist: aioredis (<2)
Requires-Dist: auth0-python
Requires-Dist: boto3 (<2)
Requires-Dist: click
Requires-Dist: click-log
Requires-Dist: cryptography (==3.4.7)
Requires-Dist: dnspython (==2.2.0)
Requires-Dist: elasticsearch (>8)
Requires-Dist: fastapi
Requires-Dist: pyyaml
Requires-Dist: redis (<5)
Requires-Dist: requests
Requires-Dist: web3 (<6,>5.0)
Requires-Dist: wsproto (==1.2.0)
